.editorconfig
.env
.gitignore
LICENSE
MANIFEST.in
Pipfile
Pipfile.lock
README.md
azure-pipelines.yml
setup.py
tox.ini
brewblox_mdns/__init__.py
brewblox_mdns/__main__.py
brewblox_mdns/dns_discovery.py
brewblox_mdns.egg-info/PKG-INFO
brewblox_mdns.egg-info/SOURCES.txt
brewblox_mdns.egg-info/dependency_links.txt
brewblox_mdns.egg-info/requires.txt
brewblox_mdns.egg-info/top_level.txt
docker/.gitignore
docker/amd/Dockerfile
docker/arm/Dockerfile
test/__init__.py
test/conftest.py
test/test_dns_discovery.py
test/test_main.py