Metadata-Version: 1.2
Name: brewblox-mdns
Version: 0.2.2.dev9
Summary: mDNS support for BrewBlox systems
Home-page: https://github.com/BrewBlox/brewblox-mdns
Author: BrewPi
Author-email: Development@brewpi.com
License: GPLv3
Keywords: brewing brewpi brewblox embedded plugin service
Platform: UNKNOWN
Classifier: Development Status :: 4 - Beta
Classifier: License :: OSI Approved :: GNU General Public License (GPL)
Classifier: Programming Language :: Python :: 3.7
Classifier: Intended Audience :: End Users/Desktop
Classifier: Topic :: System :: Hardware
Requires-Python: >=3.7
